gine/__init__.py
gine/_version.py
gine/example.py
gine/gine_widget.py
gine/netlist_graph.py
gine/utils.py
gine/labextension/package.json
gine/labextension/static/164.ccbce818c71e698b5824.js
gine/labextension/static/57.6add3cf461319140237f.js
gine/labextension/static/908.bb7c395ea7ba643e1dec.js
gine/labextension/static/remoteEntry.2512ac4c23de10d7a76f.js
gine/labextension/static/style.js
gine/labextension/static/third-party-licenses.json
gine/nbextension/extension.js
gine/nbextension/index.js
gine-0.0.9.data/data/etc/jupyter/nbconfig/notebook.d/gine.json
gine-0.0.9.data/data/share/jupyter/labextensions/gine/install.json
gine-0.0.9.data/data/share/jupyter/labextensions/gine/package.json
gine-0.0.9.data/data/share/jupyter/labextensions/gine/static/164.ccbce818c71e698b5824.js
gine-0.0.9.data/data/share/jupyter/labextensions/gine/static/57.6add3cf461319140237f.js
gine-0.0.9.data/data/share/jupyter/labextensions/gine/static/908.bb7c395ea7ba643e1dec.js
gine-0.0.9.data/data/share/jupyter/labextensions/gine/static/remoteEntry.2512ac4c23de10d7a76f.js
gine-0.0.9.data/data/share/jupyter/labextensions/gine/static/style.js
gine-0.0.9.data/data/share/jupyter/labextensions/gine/static/third-party-licenses.json
gine-0.0.9.data/data/share/jupyter/nbextensions/gine/extension.js
gine-0.0.9.data/data/share/jupyter/nbextensions/gine/index.js
gine-0.0.9.dist-info/METADATA
gine-0.0.9.dist-info/WHEEL
gine-0.0.9.dist-info/top_level.txt
gine-0.0.9.dist-info/RECORD
