Metadata-Version: 2.1
Name: gine
Version: 0.0.9
Summary: Interactive netlist visualisation tools compatible with GDSFactory
Home-page: https://github.com/daquintero/gine
Author: Dario Quintero
Author-email: darioaquintero@gmail.com
License: BSD 3-Clause License
Keywords: ipython,widgets,Jupyter,JupyterLab,JupyterLab3
Classifier: License :: OSI Approved :: BSD License
Classifier: Development Status :: 4 - Beta
Classifier: Framework :: IPython
Classifier: Intended Audience :: Developers
Classifier: Intended Audience :: Science/Research
Classifier: Programming Language :: Python
Classifier: Programming Language :: Python :: 3.7
Classifier: Programming Language :: Python :: 3.8
Classifier: Programming Language :: Python :: 3.9
Classifier: Programming Language :: Python :: 3.10
Classifier: Framework :: Jupyter
Classifier: Framework :: Jupyter :: JupyterLab
Classifier: Framework :: Jupyter :: JupyterLab :: 3
Classifier: Framework :: Jupyter :: JupyterLab :: Extensions
Classifier: Framework :: Jupyter :: JupyterLab :: Extensions :: Prebuilt
Requires-Python: >=3.7
Requires-Dist: ipywidgets (<9,>=7.6.0)
Requires-Dist: jupyter-packaging (~=0.7.9)
Requires-Dist: jupyterlab (~=3.0)
Requires-Dist: setuptools (>=40.8.0)
Requires-Dist: wheel
